lerc/Lerc.dll
lerc/Lerc.lib
lerc/__init__.py
lerc/_lerc.py
lerc/libLerc.dylib
lerc/libLerc.so.4
lerc-4.0.1.dist-info/METADATA
lerc-4.0.1.dist-info/WHEEL
lerc-4.0.1.dist-info/top_level.txt
lerc-4.0.1.dist-info/RECORD
