Metadata-Version: 2.1
Name: lerc
Version: 4.0.1
Summary: Limited Error Raster Compression
Home-page: https://github.com/Esri/lerc
Author: esri
Author-email: python@esri.com
License: Apache 2
Classifier: Programming Language :: Python :: 3
Classifier: License :: OSI Approved :: Apache Software License
Classifier: Operating System :: OS Independent
Requires-Python: >=3.6
